Metadata-Version: 1.2
Name: speedparser3
Version: 0.3.0
Summary: Python3 version of speedparser https://github.com/jmoiron/speedparser
Home-page: https://github.com/nikegp/speedparser3
Author: Nike Gurin-Petrovych
Author-email: nike.gurin@gmail.com
License: MIT
Keywords: feedparser speedparser rss atom rdf lxml python3
Platform: UNKNOWN
Classifier: License :: OSI Approved :: MIT License
Classifier: Intended Audience :: Developers
Classifier: Operating System :: POSIX
Classifier: Development Status :: 4 - Beta
Requires-Python: >=3.5
